{
    "accelerator_frequency": "",
    "accelerator_host_interconnect": "PCIe Gen5 x16",
    "accelerator_interconnect": "18x 5th Gen NVLink, 14.4 TB/s aggregated bandwidth",
    "accelerator_interconnect_topology": "",
    "accelerator_memory_capacity": "180 GB",
    "accelerator_memory_configuration": "HBM3e",
    "accelerator_model_name": "NVIDIA B200-SXM-180GB",
    "accelerator_on-chip_memories": "",
    "accelerators_per_node": 8,
    "boot_firmware_version": "",
    "cooling": "Liquid-cooled",
    "disk_controllers": "",
    "disk_drives": "",
    "division": "closed",
    "filesystem": "",
    "framework": "TensorRT 10.14, CUDA 13.1",
    "host_memory_capacity": "2 TiB",
    "host_memory_configuration": "DDR5",
    "host_network_card_count": "8x ConnectX-7 NDR 400G InfiniBand (MT4129), 4x ConnectX-7 100G InfiniBand (MT4129), 9x ConnectX-6 100G Ethernet (MT4126)",
    "host_networking": "InfiniBand NDR 400 Gb/s",
    "host_networking_topology": "InfiniBand on switching network",
    "host_processor_caches": "",
    "host_processor_core_count": 64,
    "host_processor_frequency": "",
    "host_processor_interconnect": "",
    "host_processor_model_name": "Intel(R) Xeon(R) Platinum 8562Y+",
    "host_processors_per_node": 2,
    "host_storage_capacity": "28 TB NVMe RAID10 local, 500 TB Vast NFS (shared), 10 TB Vast NFS (home)",
    "host_storage_type": "NVMe SSD (RAID10), Vast NFS",
    "hw_notes": "B200 SXM",
    "management_firmware_version": "",
    "network_speed_mbit": "",
    "nics_enabled_connected": "",
    "nics_enabled_firmware": "",
    "nics_enabled_os": "",
    "number_of_nodes": 2,
    "number_of_type_nics_installed": "",
    "operating_system": "Ubuntu 24.04",
    "other_hardware": "",
    "other_software_stack": "TensorRT 10.14, CUDA 13.1, cuDNN 9.17, Driver 580.67",
    "power_management": "",
    "power_supply_details": "",
    "power_supply_quantity_and_rating_watts": "",
    "status": "available",
    "submitter": "CoreWeave",
    "sw_notes": "",
    "system_name": "CoreWeave B200 SXM (16x B200-SXM-180GB, TensorRT)",
    "system_type": "datacenter",
    "system_type_detail": ""
}
