[
{ "seq_id" : 0, "qsl_idx" : 45586, "data" : "DF020000" },
{ "seq_id" : 2, "qsl_idx" : 36135, "data" : "3A020000" },
{ "seq_id" : 4, "qsl_idx" : 10316, "data" : "5F010000" },
{ "seq_id" : 1, "qsl_idx" : 18853, "data" : "A7020000" },
{ "seq_id" : 3, "qsl_idx" : 46263, "data" : "E5010000" },
{ "seq_id" : 5, "qsl_idx" : 22396, "data" : "FE020000" },
{ "seq_id" : 7, "qsl_idx" : 15487, "data" : "35000000" },
{ "seq_id" : 9, "qsl_idx" : 6215, "data" : "01000000" },
{ "seq_id" : 11, "qsl_idx" : 402, "data" : "FE010000" },
{ "seq_id" : 13, "qsl_idx" : 46032, "data" : "DC020000" },
{ "seq_id" : 15, "qsl_idx" : 38931, "data" : "04030000" },
{ "seq_id" : 17, "qsl_idx" : 29537, "data" : "92010000" },
{ "seq_id" : 19, "qsl_idx" : 27392, "data" : "8E020000" },
{ "seq_id" : 21, "qsl_idx" : 26128, "data" : "A0010000" },
{ "seq_id" : 23, "qsl_idx" : 41359, "data" : "A5010000" },
{ "seq_id" : 25, "qsl_idx" : 19616, "data" : "50010000" },
{ "seq_id" : 27, "qsl_idx" : 12803, "data" : "D0030000" },
{ "seq_id" : 29, "qsl_idx" : 1554, "data" : "B9000000" },
{ "seq_id" : 6, "qsl_idx" : 13669, "data" : "FE000000" },
{ "seq_id" : 8, "qsl_idx" : 40727, "data" : "A5030000" },
{ "seq_id" : 10, "qsl_idx" : 7537, "data" : "E6010000" },
{ "seq_id" : 12, "qsl_idx" : 26657, "data" : "BB030000" },
{ "seq_id" : 14, "qsl_idx" : 4172, "data" : "6E010000" },
{ "seq_id" : 16, "qsl_idx" : 24967, "data" : "C6020000" },
{ "seq_id" : 18, "qsl_idx" : 22845, "data" : "DB030000" },
{ "seq_id" : 20, "qsl_idx" : 9545, "data" : "AF000000" },
{ "seq_id" : 22, "qsl_idx" : 47144, "data" : "CC020000" },
{ "seq_id" : 24, "qsl_idx" : 44475, "data" : "2F010000" },
{ "seq_id" : 26, "qsl_idx" : 25035, "data" : "0C030000" },
{ "seq_id" : 28, "qsl_idx" : 38792, "data" : "90000000" },
{ "seq_id" : 30, "qsl_idx" : 21712, "data" : "E5030000" },
{ "seq_id" : 32, "qsl_idx" : 45754, "data" : "B9000000" },
{ "seq_id" : 34, "qsl_idx" : 31634, "data" : "97010000" },
{ "seq_id" : 36, "qsl_idx" : 45449, "data" : "2D030000" },
{ "seq_id" : 38, "qsl_idx" : 46935, "data" : "22030000" },
{ "seq_id" : 40, "qsl_idx" : 9768, "data" : "88030000" },
{ "seq_id" : 42, "qsl_idx" : 6535, "data" : "26020000" },
{ "seq_id" : 44, "qsl_idx" : 27475, "data" : "B8030000" },
{ "seq_id" : 46, "qsl_idx" : 43846, "data" : "F8020000" },
{ "seq_id" : 48, "qsl_idx" : 49399, "data" : "54030000" },
{ "seq_id" : 50, "qsl_idx" : 40718, "data" : "67030000" },
{ "seq_id" : 52, "qsl_idx" : 30701, "data" : "60000000" },
{ "seq_id" : 54, "qsl_idx" : 43784, "data" : "BA030000" },
{ "seq_id" : 31, "qsl_idx" : 49221, "data" : "A0010000" },
{ "seq_id" : 33, "qsl_idx" : 6406, "data" : "1F010000" },
{ "seq_id" : 35, "qsl_idx" : 26147, "data" : "70030000" },
{ "seq_id" : 37, "qsl_idx" : 19114, "data" : "AC000000" },
{ "seq_id" : 39, "qsl_idx" : 36094, "data" : "50010000" },
{ "seq_id" : 41, "qsl_idx" : 45096, "data" : "9E030000" },
{ "seq_id" : 43, "qsl_idx" : 17262, "data" : "54020000" },
{ "seq_id" : 45, "qsl_idx" : 29547, "data" : "33030000" },
{ "seq_id" : 47, "qsl_idx" : 26339, "data" : "7F000000" },
{ "seq_id" : 49, "qsl_idx" : 49649, "data" : "06010000" },
{ "seq_id" : 51, "qsl_idx" : 16065, "data" : "78000000" },
{ "seq_id" : 53, "qsl_idx" : 3150, "data" : "1A020000" },
{ "seq_id" : 55, "qsl_idx" : 7566, "data" : "A8010000" },
{ "seq_id" : 57, "qsl_idx" : 48058, "data" : "98030000" },
{ "seq_id" : 59, "qsl_idx" : 44714, "data" : "22010000" },
{ "seq_id" : 61, "qsl_idx" : 10023, "data" : "9B020000" },
{ "seq_id" : 63, "qsl_idx" : 47537, "data" : "AA030000" },
{ "seq_id" : 65, "qsl_idx" : 46159, "data" : "4E030000" },
{ "seq_id" : 67, "qsl_idx" : 28511, "data" : "C7030000" },
{ "seq_id" : 69, "qsl_idx" : 34853, "data" : "85020000" },
{ "seq_id" : 71, "qsl_idx" : 28068, "data" : "E4020000" },
{ "seq_id" : 73, "qsl_idx" : 30571, "data" : "AE030000" },
{ "seq_id" : 75, "qsl_idx" : 41961, "data" : "C8010000" },
{ "seq_id" : 77, "qsl_idx" : 9495, "data" : "B9020000" },
{ "seq_id" : 79, "qsl_idx" : 20971, "data" : "D2010000" },
{ "seq_id" : 56, "qsl_idx" : 14660, "data" : "E3010000" },
{ "seq_id" : 58, "qsl_idx" : 11999, "data" : "

...

 "95020000" },
{ "seq_id" : 49929, "qsl_idx" : 47819, "data" : "32010000" },
{ "seq_id" : 49931, "qsl_idx" : 3707, "data" : "1B030000" },
{ "seq_id" : 49933, "qsl_idx" : 14738, "data" : "B8030000" },
{ "seq_id" : 49935, "qsl_idx" : 15315, "data" : "37030000" },
{ "seq_id" : 49937, "qsl_idx" : 8405, "data" : "92010000" },
{ "seq_id" : 49939, "qsl_idx" : 48155, "data" : "3E030000" },
{ "seq_id" : 49940, "qsl_idx" : 20277, "data" : "CD010000" },
{ "seq_id" : 49942, "qsl_idx" : 3360, "data" : "8B000000" },
{ "seq_id" : 49944, "qsl_idx" : 34381, "data" : "A1000000" },
{ "seq_id" : 49946, "qsl_idx" : 27738, "data" : "CF010000" },
{ "seq_id" : 49948, "qsl_idx" : 28549, "data" : "B1010000" },
{ "seq_id" : 49950, "qsl_idx" : 18967, "data" : "C7030000" },
{ "seq_id" : 49952, "qsl_idx" : 1169, "data" : "8D020000" },
{ "seq_id" : 49954, "qsl_idx" : 13061, "data" : "4B010000" },
{ "seq_id" : 49956, "qsl_idx" : 49019, "data" : "6B000000" },
{ "seq_id" : 49958, "qsl_idx" : 25138, "data" : "82030000" },
{ "seq_id" : 49960, "qsl_idx" : 15157, "data" : "D2030000" },
{ "seq_id" : 49962, "qsl_idx" : 19347, "data" : "85030000" },
{ "seq_id" : 49964, "qsl_idx" : 8406, "data" : "29000000" },
{ "seq_id" : 49941, "qsl_idx" : 29940, "data" : "50010000" },
{ "seq_id" : 49943, "qsl_idx" : 6430, "data" : "14010000" },
{ "seq_id" : 49945, "qsl_idx" : 15074, "data" : "72020000" },
{ "seq_id" : 49947, "qsl_idx" : 8594, "data" : "42000000" },
{ "seq_id" : 49949, "qsl_idx" : 12745, "data" : "22000000" },
{ "seq_id" : 49951, "qsl_idx" : 48951, "data" : "08000000" },
{ "seq_id" : 49953, "qsl_idx" : 39836, "data" : "48030000" },
{ "seq_id" : 49955, "qsl_idx" : 24256, "data" : "6B010000" },
{ "seq_id" : 49957, "qsl_idx" : 38308, "data" : "76000000" },
{ "seq_id" : 49959, "qsl_idx" : 16510, "data" : "F5020000" },
{ "seq_id" : 49961, "qsl_idx" : 37188, "data" : "EB020000" },
{ "seq_id" : 49963, "qsl_idx" : 10435, "data" : "1C010000" },
{ "seq_id" : 49965, "qsl_idx" : 3662, "data" : "3F030000" },
{ "seq_id" : 49967, "qsl_idx" : 42454, "data" : "F9010000" },
{ "seq_id" : 49969, "qsl_idx" : 11546, "data" : "B9020000" },
{ "seq_id" : 49971, "qsl_idx" : 6713, "data" : "9C030000" },
{ "seq_id" : 49973, "qsl_idx" : 34001, "data" : "B6020000" },
{ "seq_id" : 49975, "qsl_idx" : 34829, "data" : "10030000" },
{ "seq_id" : 49977, "qsl_idx" : 49939, "data" : "17020000" },
{ "seq_id" : 49979, "qsl_idx" : 21271, "data" : "B8000000" },
{ "seq_id" : 49981, "qsl_idx" : 13541, "data" : "06020000" },
{ "seq_id" : 49983, "qsl_idx" : 30218, "data" : "1E030000" },
{ "seq_id" : 49985, "qsl_idx" : 45946, "data" : "E7020000" },
{ "seq_id" : 49987, "qsl_idx" : 30324, "data" : "C8020000" },
{ "seq_id" : 49989, "qsl_idx" : 23799, "data" : "B4030000" },
{ "seq_id" : 49966, "qsl_idx" : 14720, "data" : "F2000000" },
{ "seq_id" : 49968, "qsl_idx" : 29402, "data" : "10030000" },
{ "seq_id" : 49970, "qsl_idx" : 14848, "data" : "3C000000" },
{ "seq_id" : 49972, "qsl_idx" : 24375, "data" : "57010000" },
{ "seq_id" : 49974, "qsl_idx" : 31821, "data" : "73000000" },
{ "seq_id" : 49976, "qsl_idx" : 32081, "data" : "08000000" },
{ "seq_id" : 49978, "qsl_idx" : 2146, "data" : "15010000" },
{ "seq_id" : 49980, "qsl_idx" : 11034, "data" : "6C000000" },
{ "seq_id" : 49982, "qsl_idx" : 41041, "data" : "94030000" },
{ "seq_id" : 49984, "qsl_idx" : 42834, "data" : "C0020000" },
{ "seq_id" : 49986, "qsl_idx" : 11167, "data" : "94010000" },
{ "seq_id" : 49988, "qsl_idx" : 15740, "data" : "9A000000" },
{ "seq_id" : 49990, "qsl_idx" : 6222, "data" : "38030000" },
{ "seq_id" : 49991, "qsl_idx" : 27675, "data" : "81000000" },
{ "seq_id" : 49993, "qsl_idx" : 25501, "data" : "A7030000" },
{ "seq_id" : 49995, "qsl_idx" : 3661, "data" : "7E000000" },
{ "seq_id" : 49997, "qsl_idx" : 44264, "data" : "50010000" },
{ "seq_id" : 49999, "qsl_idx" : 10769, "data" : "F1010000" },
{ "seq_id" : 49992, "qsl_idx" : 41328, "data" : "52000000" },
{ "seq_id" : 49994, "qsl_idx" : 47387, "data" : "DB030000" },
{ "seq_id" : 49996, "qsl_idx" : 29029, "data" : "48000000" },
{ "seq_id" : 49998, "qsl_idx" : 38296, "data" : "D7010000" }
]
